{
  "updated": "2026-02-26T05:13:14.711Z",
  "market": "closed",
  "count": 21,
  "prices": {
    "WOW": {
      "t": "WOW",
      "p": 36.17,
      "pc": 35.63,
      "c": 0.54,
      "cp": 1.52,
      "v": 3787047,
      "ms": "postpost",
      "cur": "A$"
    },
    "XRO": {
      "t": "XRO",
      "p": 82.5,
      "pc": 75.76,
      "c": 6.74,
      "cp": 8.9,
      "v": 1123182,
      "ms": "postpost",
      "cur": "A$"
    },
    "WTC": {
      "t": "WTC",
      "p": 48.99,
      "pc": 47.74,
      "c": 1.25,
      "cp": 2.62,
      "v": 3225987,
      "ms": "postpost",
      "cur": "A$"
    },
    "DRO": {
      "t": "DRO",
      "p": 3.7,
      "pc": 3.39,
      "c": 0.31,
      "cp": 9.14,
      "v": 16162291,
      "ms": "postpost",
      "cur": "A$"
    },
    "PME": {
      "t": "PME",
      "p": 126.79,
      "pc": 116.23,
      "c": 10.56,
      "cp": 9.09,
      "v": 603677,
      "ms": "postpost",
      "cur": "A$"
    },
    "GYG": {
      "t": "GYG",
      "p": 19.21,
      "pc": 18,
      "c": 1.21,
      "cp": 6.72,
      "v": 970335,
      "ms": "postpost",
      "cur": "A$"
    },
    "CSL": {
      "t": "CSL",
      "p": 146.04,
      "pc": 145.11,
      "c": 0.93,
      "cp": 0.64,
      "v": 842644,
      "ms": "postpost",
      "cur": "A$"
    },
    "MQG": {
      "t": "MQG",
      "p": 209.99,
      "pc": 207.12,
      "c": 2.87,
      "cp": 1.39,
      "v": 284014,
      "ms": "postpost",
      "cur": "A$"
    },
    "GMG": {
      "t": "GMG",
      "p": 28.74,
      "pc": 28.42,
      "c": 0.32,
      "cp": 1.13,
      "v": 1487954,
      "ms": "postpost",
      "cur": "A$"
    },
    "WDS": {
      "t": "WDS",
      "p": 27.96,
      "pc": 28.24,
      "c": -0.28,
      "cp": -0.99,
      "v": 3076385,
      "ms": "postpost",
      "cur": "A$"
    },
    "SIG": {
      "t": "SIG",
      "p": 2.95,
      "pc": 2.99,
      "c": -0.04,
      "cp": -1.34,
      "v": 36490834,
      "ms": "postpost",
      "cur": "A$"
    },
    "FMG": {
      "t": "FMG",
      "p": 20.99,
      "pc": 21.14,
      "c": -0.15,
      "cp": -0.71,
      "v": 5579342,
      "ms": "postpost",
      "cur": "A$"
    },
    "DXS": {
      "t": "DXS",
      "p": 6.67,
      "pc": 6.62,
      "c": 0.05,
      "cp": 0.76,
      "v": 862467,
      "ms": "postpost",
      "cur": "A$"
    },
    "NAB": {
      "t": "NAB",
      "p": 49.08,
      "pc": 49.1,
      "c": -0.02,
      "cp": -0.04,
      "v": 1650940,
      "ms": "postpost",
      "cur": "A$"
    },
    "BHP": {
      "t": "BHP",
      "p": 57.82,
      "pc": 56.51,
      "c": 1.31,
      "cp": 2.32,
      "v": 9489094,
      "ms": "postpost",
      "cur": "A$"
    },
    "HRZ": {
      "t": "HRZ",
      "p": 1.09,
      "pc": 1.11,
      "c": -0.02,
      "cp": -1.8,
      "v": 1214131,
      "ms": "postpost",
      "cur": "A$"
    },
    "OCL": {
      "t": "OCL",
      "p": 12.79,
      "pc": 13.87,
      "c": -1.08,
      "cp": -7.79,
      "v": 112909,
      "ms": "postpost",
      "cur": "A$"
    },
    "RFG": {
      "t": "RFG",
      "p": 1.06,
      "pc": 1.13,
      "c": -0.07,
      "cp": -6.19,
      "v": 77607,
      "ms": "postpost",
      "cur": "A$"
    },
    "CBA": {
      "t": "CBA",
      "p": 177.87,
      "pc": 178.68,
      "c": -0.81,
      "cp": -0.45,
      "v": 957100,
      "ms": "postpost",
      "cur": "A$"
    },
    "RIO": {
      "t": "RIO",
      "p": 168.36,
      "pc": 162.67,
      "c": 5.69,
      "cp": 3.5,
      "v": 997351,
      "ms": "postpost",
      "cur": "A$"
    },
    "WOR": {
      "t": "WOR",
      "p": 11.82,
      "pc": 13.04,
      "c": -1.22,
      "cp": -9.36,
      "v": 4675666,
      "ms": "postpost",
      "cur": "A$"
    }
  }
}